COPYING.txt
MANIFEST.in
README.md
setup.py
pg_python2/__init__.py
pg_python2/_db_object.py
pg_python2/_delete.py
pg_python2/_read.py
pg_python2/_update.py
pg_python2/_write.py
pg_python2/pg_chrome_response.py
pg_python2/pg_chunks.py
pg_python2/pg_crawler.py
pg_python2/pg_dates.py
pg_python2/pg_excel.py
pg_python2/pg_local.py
pg_python2/pg_net.py
pg_python2/pg_python.py
pg_python2/pg_response.py
pg_python2/pg_table.py
pg_python2/pg_test.py
pg_python2/pg_time.py
pg_python2/pg_translate.py
pg_python2/pg_validate.py
pg_python2.egg-info/PKG-INFO
pg_python2.egg-info/SOURCES.txt
pg_python2.egg-info/dependency_links.txt
pg_python2.egg-info/not-zip-safe
pg_python2.egg-info/top_level.txt