Metadata-Version: 1.1
Name: pg-python2
Version: 1.0.3
Summary: A Library to communicate with postgres from python
Home-page: http://github.com/ingloriousb/pg_python2
Author: Gaurav Bhati
Author-email: gaurav.hawker@gmail.com
License: MIT License
Platform: any
Classifier: Programming Language :: Python
Classifier: Programming Language :: Python :: 2
Classifier: Development Status :: 4 - Beta
Classifier: Natural Language :: English
Classifier: Environment :: Web Environment
Classifier: Intended Audience :: Developers
Classifier: License :: OSI Approved :: MIT License
Classifier: Operating System :: OS Independent
Classifier: Topic :: Software Development :: Libraries :: Python Modules
Classifier: Topic :: Software Development :: Libraries :: Application Frameworks
Classifier: Topic :: Internet :: WWW/HTTP :: Dynamic Content
